stockdatamanager/__init__.py
stockdatamanager/customerrors.py
stockdatamanager/datafetcher.py
stockdatamanager/indicators.py
stockdatamanager/options.py
stockdatamanager/utils.py
stockdatamanager-1.1.2.dist-info/LICENSE
stockdatamanager-1.1.2.dist-info/METADATA
stockdatamanager-1.1.2.dist-info/WHEEL
stockdatamanager-1.1.2.dist-info/top_level.txt
stockdatamanager-1.1.2.dist-info/RECORD
