Metadata-Version: 2.1
Name: stockdatamanager
Version: 1.1.2
Summary: A comprehensive library for financial analysis
Home-page: https://github.com/GiorgioMB/stockdatafetcher/
Author: Giorgio Micaletto
Author-email: giorgio.micaletto@studbocconi.it
Requires-Python: >=3.6
License-File: LICENSE
Requires-Dist: pandas >=1.1.5
Requires-Dist: yfinance >=0.1.63
Requires-Dist: requests >=2.25.1
Requires-Dist: pylint >=2.6.0
Requires-Dist: pandas-datareader >=0.10.0
Requires-Dist: numpy >=1.23
Requires-Dist: scipy >=1.7.1
Requires-Dist: matplotlib >=3.4.2
Requires-Dist: seaborn >=0.11.1
Requires-Dist: scikit-learn >=1.4.1.post1
Requires-Dist: statsmodels >=0.14.1
Requires-Dist: arch >=4.19
Requires-Dist: optuna >=2.10.0
Requires-Dist: torch >=2.2.1
